adapters/__init__.py
adapters/source/__init__.py
adapters/source/base_adapter.py
adapters/source/extjs_parser.py
adapters/source/extjs_tree_sitter_parser.py
adapters/source/js_adapter.py
adapters/source/xhtml_adapter.py
adapters/target/__init__.py
agents/__init__.py
agents/ast/__init__.py
agents/ast/source_ast_agent.py
agents/dependency/__init__.py
agents/dependency/dependency_agent.py
agents/documentation/__init__.py
agents/generation/__init__.py
agents/generation/code_generation_agent.py
agents/generation/target_code_generation.py
agents/ir/__init__.py
agents/ir/canonical_ir_agent.py
agents/ir/ir_normalization_agent.py
agents/mapping/__init__.py
agents/mapping/target_mapping_agent.py
agents/migration/__init__.py
agents/migration/migration_planning_agent.py
agents/scanner/__init__.py
agents/scanner/scanner_agent.py
cli/__init__.py
cli/main.py
code_transformer_platform-1.0.0.dist-info/licenses/LICENSE
config/__init__.py
config/config_loader.py
config/settings.py
config/llm/__init__.py
config/llm/azure_openai.yaml
config/llm/generation_policy.yaml
config/targets/angular18.yaml
core/__init__.py
core/agent.py
core/artifacts.py
core/azure_openai_client.py
core/context.py
core/documentation_writer.py
core/llm_client.py
core/orchestrator.py
models/__init__.py
models/canonical_ir.py
models/documentation.py
models/migration_plan.py
models/targets_ir.py
code_transformer_platform-1.0.0.dist-info/METADATA
code_transformer_platform-1.0.0.dist-info/WHEEL
code_transformer_platform-1.0.0.dist-info/entry_points.txt
code_transformer_platform-1.0.0.dist-info/top_level.txt
code_transformer_platform-1.0.0.dist-info/RECORD
