Metadata-Version: 2.4
Name: code-transformer-platform
Version: 1.0.0
Summary: AI-powered code migration platform for transforming legacy codebases to modern frameworks
Author-email: Modernization Expert <digitalneeds.tech@gmail.com>
License-Expression: MIT
Project-URL: Homepage, https://github.com/digitalneedstech/code-transformer-platform
Project-URL: Documentation, https://github.com/digitalneedstech/code-transformer-platform#readme
Project-URL: Repository, https://github.com/digitalneedstech/code-transformer-platform
Project-URL: Issues, https://github.com/digitalneedstech/code-transformer-platform/issues
Keywords: code-migration,code-transformation,ai,llm,extjs,angular,modernization
Classifier: Development Status :: 3 - Alpha
Classifier: Intended Audience :: Developers
Classifier: Topic :: Software Development :: Code Generators
Classifier: Topic :: Software Development :: Libraries :: Python Modules
Classifier: Programming Language :: Python :: 3
Classifier: Programming Language :: Python :: 3.8
Classifier: Programming Language :: Python :: 3.9
Classifier: Programming Language :: Python :: 3.10
Classifier: Programming Language :: Python :: 3.11
Classifier: Programming Language :: Python :: 3.12
Requires-Python: >=3.8
License-File: LICENSE
Requires-Dist: pydantic>=2.0.0
Requires-Dist: openai>=1.0.0
Requires-Dist: python-dotenv>=1.0.0
Requires-Dist: pyyaml>=6.0
Requires-Dist: tree-sitter>=0.20.0
Requires-Dist: tree-sitter-javascript>=0.20.0
Provides-Extra: dev
Requires-Dist: pytest>=7.0.0; extra == "dev"
Requires-Dist: pytest-cov>=4.0.0; extra == "dev"
Requires-Dist: black>=23.0.0; extra == "dev"
Requires-Dist: flake8>=6.0.0; extra == "dev"
Requires-Dist: mypy>=1.0.0; extra == "dev"
Dynamic: license-file
